{"cameraMode":{"drawMode":0,"name":"Shaded","section":"Shading Mode"},"sceneLighting":true,"audioPlay":false,"sceneViewState":{"m_AlwaysRefresh":false,"showFog":true,"showSkybox":true,"showFlares":true,"showImageEffects":true,"showParticleSystems":true,"showVisualEffectGraphs":true,"m_FxEnabled":true},"in2DMode":false,"pivot":{"x":500.3018798828125,"y":289.31036376953127,"z":-220.6378631591797},"rotation":{"x":0.1168188601732254,"y":-0.06104385852813721,"z":0.007195207290351391,"w":0.9912462830543518},"size":224.93577575683595,"orthographic":false}